Metadata-Version: 1.0
Name: lyricwikia
Version: 0.1.6
Summary: LyricWikia API for song lyrics
Home-page: http://github.com/enricobacis/lyricwikia
Author: Enrico Bacis
Author-email: enrico.bacis@gmail.com
License: MIT
Keywords: lyricwikia lyric lyrics wikia song api
Platform: UNKNOWN
